asymmetric_jwt_auth/__init__.py
asymmetric_jwt_auth/admin.py
asymmetric_jwt_auth/apps.py
asymmetric_jwt_auth/keys.py
asymmetric_jwt_auth/middleware.py
asymmetric_jwt_auth/models.py
asymmetric_jwt_auth/py.typed
asymmetric_jwt_auth/tokens.py
asymmetric_jwt_auth/urls.py
asymmetric_jwt_auth/utils.py
asymmetric_jwt_auth/views.py
asymmetric_jwt_auth/management/__init__.py
asymmetric_jwt_auth/management/commands/__init__.py
asymmetric_jwt_auth/management/commands/generate_key_pair.py
asymmetric_jwt_auth/migrations/0001_initial.py
asymmetric_jwt_auth/migrations/0002_publickey_comment.py
asymmetric_jwt_auth/migrations/0003_auto_20151112_1547.py
asymmetric_jwt_auth/migrations/0004_auto_20191104_1628.py
asymmetric_jwt_auth/migrations/0005_auto_20210304_1116.py
asymmetric_jwt_auth/migrations/0006_jwksendpointtrust_last_used_on_alter_publickey_key.py
asymmetric_jwt_auth/migrations/__init__.py
asymmetric_jwt_auth/nonce/__init__.py
asymmetric_jwt_auth/nonce/base.py
asymmetric_jwt_auth/nonce/django.py
asymmetric_jwt_auth/nonce/null.py
asymmetric_jwt_auth/repos/__init__.py
asymmetric_jwt_auth/repos/base.py
asymmetric_jwt_auth/repos/django.py
asymmetric_jwt_auth/tests/__init__.py
asymmetric_jwt_auth/tests/data.py
asymmetric_jwt_auth/tests/test_admin.py
asymmetric_jwt_auth/tests/test_commands.py
asymmetric_jwt_auth/tests/test_keys.py
asymmetric_jwt_auth/tests/test_middleware.py
asymmetric_jwt_auth/tests/test_models.py
asymmetric_jwt_auth/tests/test_settings.py
asymmetric_jwt_auth/tests/test_token.py
asymmetric_jwt_auth/tests/test_utils.py
asymmetric_jwt_auth/tests/test_views.py
asymmetric_jwt_auth/tests/fixtures/dummy_rsa.privkey
asymmetric_jwt_auth/tests/fixtures/dummy_rsa.pub
asymmetric_jwt_auth/tests/fixtures/dummy_rsa_encrypted.privkey
asymmetric_jwt_auth/tests/fixtures/dummy_rsa_encrypted.pub
asymmetric_jwt_auth-1.2.1.dist-info/METADATA
asymmetric_jwt_auth-1.2.1.dist-info/WHEEL
asymmetric_jwt_auth-1.2.1.dist-info/licenses/LICENSE.md
asymmetric_jwt_auth-1.2.1.dist-info/RECORD
