Metadata-Version: 2.4
Name: asymmetric-jwt-auth
Version: 1.2.1
Summary: Asymmetric key based authentication for HTTP APIs
Project-URL: Homepage, https://gitlab.com/thelabnyc/asymmetric-jwt-auth
Project-URL: Repository, https://gitlab.com/thelabnyc/asymmetric-jwt-auth
Author-email: Craig Weber <crgwbr@gmail.com>, Craig Weber <crgwbr@gmail.com>
License: ISC
License-File: LICENSE.md
Classifier: Development Status :: 5 - Production/Stable
Classifier: Environment :: Web Environment
Classifier: Framework :: Django
Classifier: Intended Audience :: Developers
Classifier: License :: OSI Approved :: ISC License (ISCL)
Requires-Python: >=3.11
Requires-Dist: cryptography>=44.0.2
Requires-Dist: django>=4.2
Requires-Dist: pyjwt<3,>=2.10.1
